crlbuilder/__init__.py
crlbuilder-0.10.2.dist-info/DESCRIPTION.rst
crlbuilder-0.10.2.dist-info/METADATA
crlbuilder-0.10.2.dist-info/RECORD
crlbuilder-0.10.2.dist-info/WHEEL
crlbuilder-0.10.2.dist-info/metadata.json
crlbuilder-0.10.2.dist-info/top_level.txt
